<?xml version="1.0" encoding="UTF-8"?>
<!DOCTYPE mapper PUBLIC "-//mybatis.org//DTD Mapper 3.0//EN" 
"http://mybatis.org/dtd/mybatis-3-mapper.dtd">
<!-- tblNameCN:待发送短信或待推送消息 t_message_to_be_send -->
<mapper namespace="messageToBeSendBase">
	<resultMap type="MessageToBeSend" id="messageToBeSendBaseMap">
        <id column="f_id" javaType="java.math.BigInteger" property="id"/>  <!--  -->        <result column="f_msg_type" javaType="java.lang.Integer" property="msgType"/>  <!-- 消息类型 -->        <result column="f_title" javaType="java.lang.String" property="title"/>  <!-- 消息标题 -->        <result column="f_content" javaType="java.lang.String" property="content"/>  <!-- 消息内容 -->        <result column="f_send_range" javaType="java.lang.Integer" property="sendRange"/>  <!-- 发送范围 -->        <result column="f_send_time" javaType="java.lang.String" property="sendTime"/>  <!-- 发送时间 -->        <result column="f_send_status" javaType="java.lang.Integer" property="sendStatus"/>  <!-- 发送状态 -->        <result column="f_operator_user" javaType="java.lang.String" property="operatorUser"/>  <!-- 操作人 -->        <result column="f_send_count" javaType="java.lang.Long" property="sendCount"/>  <!-- 发送信息条数 -->        <result column="f_short_url" javaType="java.lang.String" property="shortUrl"/>  <!-- 短链接 -->        <result column="f_white_list" javaType="java.lang.String" property="whiteList"/>  <!-- 短信白名单 -->        <result column="f_black_list" javaType="java.lang.String" property="blackList"/>  <!-- 短信黑名单 -->        <result column="f_jump_target" javaType="java.lang.String" property="jumpTarget"/>  <!-- 跳转目标 -->        <result column="f_ebuy_product_detail" javaType="java.lang.String" property="ebuyProductDetail"/>  <!-- 商品详情 -->        <result column="f_sys0_add_time" javaType="java.lang.String" property="sys0AddTime"/>  <!-- 新增时间 -->        <result column="f_sys0_upd_time" javaType="java.lang.String" property="sys0UpdTime"/>  <!-- 更新时间 -->        <result column="f_sys0_del_time" javaType="java.lang.String" property="sys0DelTime"/>  <!-- 删除时间 -->        <result column="f_sys0_add_user" javaType="java.math.BigInteger" property="sys0AddUser"/>  <!-- 新增者 -->        <result column="f_sys0_upd_user" javaType="java.math.BigInteger" property="sys0UpdUser"/>  <!-- 修改者 -->        <result column="f_sys0_del_user" javaType="java.math.BigInteger" property="sys0DelUser"/>  <!-- 删除者 -->        <result column="f_sys0_del_state" javaType="java.lang.Integer" property="sys0DelState"/>  <!-- 记录状态 -->
	</resultMap>
	<resultMap type="MessageToBeSend" id="messageToBeSendExtendMap" extends="messageToBeSendBaseMap">
	</resultMap>
	<resultMap type="MessageToBeSend" id="messageToBeSendBaseMap_AppendTable">
        <id column="MTBSid" javaType="java.math.BigInteger" property="id"/>  <!--  -->        <result column="MTBSmsgType" javaType="java.lang.Integer" property="msgType"/>  <!-- 消息类型 -->        <result column="MTBStitle" javaType="java.lang.String" property="title"/>  <!-- 消息标题 -->        <result column="MTBScontent" javaType="java.lang.String" property="content"/>  <!-- 消息内容 -->        <result column="MTBSsendRange" javaType="java.lang.Integer" property="sendRange"/>  <!-- 发送范围 -->        <result column="MTBSsendTime" javaType="java.lang.String" property="sendTime"/>  <!-- 发送时间 -->        <result column="MTBSsendStatus" javaType="java.lang.Integer" property="sendStatus"/>  <!-- 发送状态 -->        <result column="MTBSoperatorUser" javaType="java.lang.String" property="operatorUser"/>  <!-- 操作人 -->        <result column="MTBSsendCount" javaType="java.lang.Long" property="sendCount"/>  <!-- 发送信息条数 -->        <result column="MTBSshortUrl" javaType="java.lang.String" property="shortUrl"/>  <!-- 短链接 -->        <result column="MTBSwhiteList" javaType="java.lang.String" property="whiteList"/>  <!-- 短信白名单 -->        <result column="MTBSblackList" javaType="java.lang.String" property="blackList"/>  <!-- 短信黑名单 -->        <result column="MTBSjumpTarget" javaType="java.lang.String" property="jumpTarget"/>  <!-- 跳转目标 -->        <result column="MTBSebuyProductDetail" javaType="java.lang.String" property="ebuyProductDetail"/>  <!-- 商品详情 -->        <result column="MTBSsys0AddTime" javaType="java.lang.String" property="sys0AddTime"/>  <!-- 新增时间 -->        <result column="MTBSsys0UpdTime" javaType="java.lang.String" property="sys0UpdTime"/>  <!-- 更新时间 -->        <result column="MTBSsys0DelTime" javaType="java.lang.String" property="sys0DelTime"/>  <!-- 删除时间 -->        <result column="MTBSsys0AddUser" javaType="java.math.BigInteger" property="sys0AddUser"/>  <!-- 新增者 -->        <result column="MTBSsys0UpdUser" javaType="java.math.BigInteger" property="sys0UpdUser"/>  <!-- 修改者 -->        <result column="MTBSsys0DelUser" javaType="java.math.BigInteger" property="sys0DelUser"/>  <!-- 删除者 -->        <result column="MTBSsys0DelState" javaType="java.lang.Integer" property="sys0DelState"/>  <!-- 记录状态 -->
	</resultMap>
	<resultMap type="MessageToBeSend" id="messageToBeSendBaseMap_AppendTable1">
        <id column="MTBS1id" javaType="java.math.BigInteger" property="id"/>  <!--  -->        <result column="MTBS1msgType" javaType="java.lang.Integer" property="msgType"/>  <!-- 消息类型 -->        <result column="MTBS1title" javaType="java.lang.String" property="title"/>  <!-- 消息标题 -->        <result column="MTBS1content" javaType="java.lang.String" property="content"/>  <!-- 消息内容 -->        <result column="MTBS1sendRange" javaType="java.lang.Integer" property="sendRange"/>  <!-- 发送范围 -->        <result column="MTBS1sendTime" javaType="java.lang.String" property="sendTime"/>  <!-- 发送时间 -->        <result column="MTBS1sendStatus" javaType="java.lang.Integer" property="sendStatus"/>  <!-- 发送状态 -->        <result column="MTBS1operatorUser" javaType="java.lang.String" property="operatorUser"/>  <!-- 操作人 -->        <result column="MTBS1sendCount" javaType="java.lang.Long" property="sendCount"/>  <!-- 发送信息条数 -->        <result column="MTBS1shortUrl" javaType="java.lang.String" property="shortUrl"/>  <!-- 短链接 -->        <result column="MTBS1whiteList" javaType="java.lang.String" property="whiteList"/>  <!-- 短信白名单 -->        <result column="MTBS1blackList" javaType="java.lang.String" property="blackList"/>  <!-- 短信黑名单 -->        <result column="MTBS1jumpTarget" javaType="java.lang.String" property="jumpTarget"/>  <!-- 跳转目标 -->        <result column="MTBS1ebuyProductDetail" javaType="java.lang.String" property="ebuyProductDetail"/>  <!-- 商品详情 -->        <result column="MTBS1sys0AddTime" javaType="java.lang.String" property="sys0AddTime"/>  <!-- 新增时间 -->        <result column="MTBS1sys0UpdTime" javaType="java.lang.String" property="sys0UpdTime"/>  <!-- 更新时间 -->        <result column="MTBS1sys0DelTime" javaType="java.lang.String" property="sys0DelTime"/>  <!-- 删除时间 -->        <result column="MTBS1sys0AddUser" javaType="java.math.BigInteger" property="sys0AddUser"/>  <!-- 新增者 -->        <result column="MTBS1sys0UpdUser" javaType="java.math.BigInteger" property="sys0UpdUser"/>  <!-- 修改者 -->        <result column="MTBS1sys0DelUser" javaType="java.math.BigInteger" property="sys0DelUser"/>  <!-- 删除者 -->        <result column="MTBS1sys0DelState" javaType="java.lang.Integer" property="sys0DelState"/>  <!-- 记录状态 -->
	</resultMap>
	<!-- 公共sql提取  -->
	<sql id="queryHead">
		MTBS.f_id,MTBS.f_msg_type,MTBS.f_title,MTBS.f_content,MTBS.f_send_range,date_format(MTBS.f_send_time,'%Y-%m-%d %T') as f_send_time,MTBS.f_send_status,MTBS.f_operator_user,MTBS.f_send_count,MTBS.f_short_url,MTBS.f_white_list,MTBS.f_black_list,MTBS.f_jump_target,MTBS.f_ebuy_product_detail
	</sql>
	<sql id="queryHead_AppendTable">
		MTBS.f_id as MTBSid,MTBS.f_msg_type as MTBSmsgType,MTBS.f_title as MTBStitle,MTBS.f_content as MTBScontent,MTBS.f_send_range as MTBSsendRange,date_format(MTBS.f_send_time,'%Y-%m-%d %T') as MTBSsendTime,MTBS.f_send_status as MTBSsendStatus,MTBS.f_operator_user as MTBSoperatorUser,MTBS.f_send_count as MTBSsendCount,MTBS.f_short_url as MTBSshortUrl,MTBS.f_white_list as MTBSwhiteList,MTBS.f_black_list as MTBSblackList,MTBS.f_jump_target as MTBSjumpTarget,MTBS.f_ebuy_product_detail as MTBSebuyProductDetail
	</sql>
	<sql id="queryHead_AppendTable1">
		MTBS1.f_id as MTBS1id,MTBS1.f_msg_type as MTBS1msgType,MTBS1.f_title as MTBS1title,MTBS1.f_content as MTBS1content,MTBS1.f_send_range as MTBS1sendRange,date_format(MTBS1.f_send_time,'%Y-%m-%d %T') as MTBS1sendTime,MTBS1.f_send_status as MTBS1sendStatus,MTBS1.f_operator_user as MTBS1operatorUser,MTBS1.f_send_count as MTBS1sendCount,MTBS1.f_short_url as MTBS1shortUrl,MTBS1.f_white_list as MTBS1whiteList,MTBS1.f_black_list as MTBS1blackList,MTBS1.f_jump_target as MTBS1jumpTarget,MTBS1.f_ebuy_product_detail as MTBS1ebuyProductDetail
	</sql>
	<sql id="querySql">
        <if test="id != null">  and (MTBS.f_id = #{id} ) </if>        <if test="msgType != null">  and (MTBS.f_msg_type = #{msgType} ) </if>        <if test="title != null">  and (MTBS.f_title = #{title} ) </if>        <if test="content != null">  and (MTBS.f_content = #{content} ) </if>        <if test="sendRange != null">  and (MTBS.f_send_range = #{sendRange} ) </if>        <if test="sendTime != null and !sendTime.equals('')  ">  and (MTBS.f_send_time = str_to_date(#{sendTime},'%Y-%m-%d %T') ) </if>        <if test="sendTime_START != null and !sendTime_START.equals('')  ">              <![CDATA[ and (MTBS.f_send_time >= str_to_date(#{sendTime_START},'%Y-%m-%d %T') ) ]]>        </if>        <if test="sendTime_END != null and !sendTime_END.equals('')  ">            <![CDATA[ and (MTBS.f_send_time <= str_to_date(#{sendTime_END},'%Y-%m-%d %T') ) ]]>        </if>        <if test="sendStatus != null">  and (MTBS.f_send_status = #{sendStatus} ) </if>        <if test="operatorUser != null">  and (MTBS.f_operator_user = #{operatorUser} ) </if>        <if test="sendCount != null">  and (MTBS.f_send_count = #{sendCount} ) </if>        <if test="shortUrl != null">  and (MTBS.f_short_url = #{shortUrl} ) </if>        <if test="whiteList != null">  and (MTBS.f_white_list = #{whiteList} ) </if>        <if test="blackList != null">  and (MTBS.f_black_list = #{blackList} ) </if>        <if test="jumpTarget != null">  and (MTBS.f_jump_target = #{jumpTarget} ) </if>        <if test="ebuyProductDetail != null">  and (MTBS.f_ebuy_product_detail = #{ebuyProductDetail} ) </if>        <if test="sys0AddTime != null and !sys0AddTime.equals('')  ">  and (MTBS.f_sys0_add_time = str_to_date(#{sys0AddTime},'%Y-%m-%d %T') ) </if>        <if test="sys0AddTime_START != null and !sys0AddTime_START.equals('')  ">              <![CDATA[ and (MTBS.f_sys0_add_time >= str_to_date(#{sys0AddTime_START},'%Y-%m-%d %T') ) ]]>        </if>        <if test="sys0AddTime_END != null and !sys0AddTime_END.equals('')  ">            <![CDATA[ and (MTBS.f_sys0_add_time <= str_to_date(#{sys0AddTime_END},'%Y-%m-%d %T') ) ]]>        </if>        <if test="sys0UpdTime != null and !sys0UpdTime.equals('')  ">  and (MTBS.f_sys0_upd_time = str_to_date(#{sys0UpdTime},'%Y-%m-%d %T') ) </if>        <if test="sys0UpdTime_START != null and !sys0UpdTime_START.equals('')  ">              <![CDATA[ and (MTBS.f_sys0_upd_time >= str_to_date(#{sys0UpdTime_START},'%Y-%m-%d %T') ) ]]>        </if>        <if test="sys0UpdTime_END != null and !sys0UpdTime_END.equals('')  ">            <![CDATA[ and (MTBS.f_sys0_upd_time <= str_to_date(#{sys0UpdTime_END},'%Y-%m-%d %T') ) ]]>        </if>        <if test="sys0DelTime != null and !sys0DelTime.equals('')  ">  and (MTBS.f_sys0_del_time = str_to_date(#{sys0DelTime},'%Y-%m-%d %T') ) </if>        <if test="sys0DelTime_START != null and !sys0DelTime_START.equals('')  ">              <![CDATA[ and (MTBS.f_sys0_del_time >= str_to_date(#{sys0DelTime_START},'%Y-%m-%d %T') ) ]]>        </if>        <if test="sys0DelTime_END != null and !sys0DelTime_END.equals('')  ">            <![CDATA[ and (MTBS.f_sys0_del_time <= str_to_date(#{sys0DelTime_END},'%Y-%m-%d %T') ) ]]>        </if>        <if test="sys0AddUser != null">  and (MTBS.f_sys0_add_user = #{sys0AddUser} ) </if>        <if test="sys0UpdUser != null">  and (MTBS.f_sys0_upd_user = #{sys0UpdUser} ) </if>        <if test="sys0DelUser != null">  and (MTBS.f_sys0_del_user = #{sys0DelUser} ) </if>        <if test="sys0DelState != null">  and (MTBS.f_sys0_del_state = #{sys0DelState} ) </if>        <if test="sys0DelState == null">  and (MTBS.f_sys0_del_state = 0 ) </if>
	</sql>
	<sql id="querySqlDim">
        <if test="id != null and !id.equals('')  ">  and (MTBS.f_id = #{id} ) </if>        <if test="msgType != null and !msgType.equals('')  ">  and (MTBS.f_msg_type = #{msgType} ) </if>        <if test="title != null and !title.equals('')  ">  and (MTBS.f_title like CONCAT('%',#{title},'%') ) </if>        <if test="content != null and !content.equals('')  ">  and (MTBS.f_content like CONCAT('%',#{content},'%') ) </if>        <if test="sendRange != null and !sendRange.equals('')  ">  and (MTBS.f_send_range = #{sendRange} ) </if>        <if test="sendTime != null and !sendTime.equals('')  ">  and (MTBS.f_send_time = str_to_date(#{sendTime},'%Y-%m-%d %T') ) </if>        <if test="sendTime_START != null and !sendTime_START.equals('')  ">              <![CDATA[ and (MTBS.f_send_time >= str_to_date(#{sendTime_START},'%Y-%m-%d %T') ) ]]>        </if>        <if test="sendTime_END != null and !sendTime_END.equals('')  ">            <![CDATA[ and (MTBS.f_send_time <= str_to_date(#{sendTime_END},'%Y-%m-%d %T') ) ]]>        </if>        <if test="sendStatus != null and !sendStatus.equals('')  ">  and (MTBS.f_send_status = #{sendStatus} ) </if>        <if test="operatorUser != null and !operatorUser.equals('')  ">  and (MTBS.f_operator_user like CONCAT('%',#{operatorUser},'%') ) </if>        <if test="sendCount != null and !sendCount.equals('')  ">  and (MTBS.f_send_count = #{sendCount} ) </if>        <if test="shortUrl != null and !shortUrl.equals('')  ">  and (MTBS.f_short_url like CONCAT('%',#{shortUrl},'%') ) </if>        <if test="whiteList != null and !whiteList.equals('')  ">  and (MTBS.f_white_list like CONCAT('%',#{whiteList},'%') ) </if>        <if test="blackList != null and !blackList.equals('')  ">  and (MTBS.f_black_list like CONCAT('%',#{blackList},'%') ) </if>        <if test="jumpTarget != null and !jumpTarget.equals('')  ">  and (MTBS.f_jump_target like CONCAT('%',#{jumpTarget},'%') ) </if>        <if test="ebuyProductDetail != null and !ebuyProductDetail.equals('')  ">  and (MTBS.f_ebuy_product_detail like CONCAT('%',#{ebuyProductDetail},'%') ) </if>        <if test="sys0AddTime != null and !sys0AddTime.equals('')  ">  and (MTBS.f_sys0_add_time = str_to_date(#{sys0AddTime},'%Y-%m-%d %T') ) </if>        <if test="sys0AddTime_START != null and !sys0AddTime_START.equals('')  ">              <![CDATA[ and (MTBS.f_sys0_add_time >= str_to_date(#{sys0AddTime_START},'%Y-%m-%d %T') ) ]]>        </if>        <if test="sys0AddTime_END != null and !sys0AddTime_END.equals('')  ">            <![CDATA[ and (MTBS.f_sys0_add_time <= str_to_date(#{sys0AddTime_END},'%Y-%m-%d %T') ) ]]>        </if>        <if test="sys0UpdTime != null and !sys0UpdTime.equals('')  ">  and (MTBS.f_sys0_upd_time = str_to_date(#{sys0UpdTime},'%Y-%m-%d %T') ) </if>        <if test="sys0UpdTime_START != null and !sys0UpdTime_START.equals('')  ">              <![CDATA[ and (MTBS.f_sys0_upd_time >= str_to_date(#{sys0UpdTime_START},'%Y-%m-%d %T') ) ]]>        </if>        <if test="sys0UpdTime_END != null and !sys0UpdTime_END.equals('')  ">            <![CDATA[ and (MTBS.f_sys0_upd_time <= str_to_date(#{sys0UpdTime_END},'%Y-%m-%d %T') ) ]]>        </if>        <if test="sys0DelTime != null and !sys0DelTime.equals('')  ">  and (MTBS.f_sys0_del_time = str_to_date(#{sys0DelTime},'%Y-%m-%d %T') ) </if>        <if test="sys0DelTime_START != null and !sys0DelTime_START.equals('')  ">              <![CDATA[ and (MTBS.f_sys0_del_time >= str_to_date(#{sys0DelTime_START},'%Y-%m-%d %T') ) ]]>        </if>        <if test="sys0DelTime_END != null and !sys0DelTime_END.equals('')  ">            <![CDATA[ and (MTBS.f_sys0_del_time <= str_to_date(#{sys0DelTime_END},'%Y-%m-%d %T') ) ]]>        </if>        <if test="sys0AddUser != null and !sys0AddUser.equals('')  ">  and (MTBS.f_sys0_add_user = #{sys0AddUser} ) </if>        <if test="sys0UpdUser != null and !sys0UpdUser.equals('')  ">  and (MTBS.f_sys0_upd_user = #{sys0UpdUser} ) </if>        <if test="sys0DelUser != null and !sys0DelUser.equals('')  ">  and (MTBS.f_sys0_del_user = #{sys0DelUser} ) </if>        <if test="sys0DelState != null and !sys0DelState.equals('')  ">  and (MTBS.f_sys0_del_state = #{sys0DelState} ) </if>        <if test="sys0DelState == null or sys0DelState == '' ">  and (MTBS.f_sys0_del_state = 0 ) </if>
	</sql>
	<sql id="dimCheckSql">
		<if test="_QUERY_TYPE_IF_DIM == true"><include refid="messageToBeSendBase.querySqlDim"/></if>
		<if test="_QUERY_TYPE_IF_DIM == null or  _QUERY_TYPE_IF_DIM == '' or  _QUERY_TYPE_IF_DIM == false or _QUERY_TYPE_IF_DIM != true"><include refid="messageToBeSendBase.querySql"/></if><!-- 默认精确查询 -->
		<!-- <if test="_QUERY_TYPE_IF_DIM != true"><include refid="messageToBeSendBase.querySql"/></if> --><!-- 默认精确查询 -->
	</sql>
	<!-- 各种查询附加的查询条件 -->
	<sql id="busiQueryCondition">
	    <include refid="messageToBeSendBase.busiQueryCount"/>
	</sql>
	<!-- 查询记录数附加的查询条件 -->
	<sql id="busiQueryCount">
	     FROM t_message_to_be_send MTBS    	 WHERE 1=1
	</sql>
	
	<!-- 根据条件查询(待发送短信或待推送消息)信息。 -->
	<sql id="select_messageToBeSend">
		SELECT <include refid="messageToBeSendBase.queryHead"/>
		<include refid="messageToBeSendBase.busiQueryCondition"/>
		<include refid="messageToBeSendBase.dimCheckSql"/>
		ORDER BY MTBS.f_id DESC
	</sql>
	<select id="select_messageToBeSend" parameterType="java.util.Map" resultMap="messageToBeSendBase.messageToBeSendExtendMap">
		<include refid="messageToBeSendBase.select_messageToBeSend"/>
	</select>
	
	<!-- 根据条件分页查询(待发送短信或待推送消息)信息  -->
	<sql id="select_messageToBeSend_withPage">
		SELECT <include refid="messageToBeSendBase.queryHead"/>
		<include refid="messageToBeSendBase.busiQueryCondition"/>
		<include refid="messageToBeSendBase.dimCheckSql"/>
		ORDER BY f_id DESC
		<![CDATA[ LIMIT #{_begin},#{_length} ]]>
	</sql>
	<select id="select_messageToBeSend_withPage" resultMap="messageToBeSendBase.messageToBeSendExtendMap" parameterType="java.util.Map">
		<include refid="messageToBeSendBase.select_messageToBeSend_withPage"/>
	</select>

	<!-- 根据序列号查询某个(待发送短信或待推送消息)信息。 -->
	<sql id="select_messageToBeSend_bySeqId">
		SELECT <include refid="messageToBeSendBase.queryHead"/>
		<include refid="messageToBeSendBase.busiQueryCondition"/>
		 and MTBS.f_id = #{_parameter}
	</sql>
	<select id="select_messageToBeSend_bySeqId" parameterType="java.math.BigInteger" resultMap="messageToBeSendBase.messageToBeSendBaseMap">
		<include refid="messageToBeSendBase.select_messageToBeSend_bySeqId"/>
	</select>
	
	<!-- 根据条件查询满足条件的(待发送短信或待推送消息)记录数  -->
	<sql id="select_messageToBeSend_count">
		SELECT COUNT(*)
		<include refid="messageToBeSendBase.busiQueryCount"/>
		<include refid="messageToBeSendBase.dimCheckSql"/>
	</sql>
	<select id="select_messageToBeSend_count" resultType="java.lang.Integer">
		<include refid="messageToBeSendBase.select_messageToBeSend_count"/>
	</select>
	
	 <!-- 往(待发送短信或待推送消息)新增一条记录。 -->
	 <sql id="insert_messageToBeSend">
		INSERT INTO t_message_to_be_send 
		(f_id,f_msg_type,f_title,f_content,f_send_range,f_send_time,f_send_status,f_operator_user,f_send_count,f_short_url,f_white_list,f_black_list,f_jump_target,f_ebuy_product_detail,f_sys0_add_time,f_sys0_upd_time,f_sys0_del_time,f_sys0_add_user,f_sys0_upd_user,f_sys0_del_user,f_sys0_del_state) VALUES 
		(#{id},#{msgType},#{title,jdbcType=VARCHAR},#{content,jdbcType=VARCHAR},#{sendRange},str_to_date(#{sendTime,jdbcType=DATE},'%Y-%m-%d %T'),#{sendStatus},#{operatorUser,jdbcType=VARCHAR},#{sendCount},#{shortUrl,jdbcType=VARCHAR},#{whiteList,jdbcType=VARCHAR},#{blackList,jdbcType=VARCHAR},#{jumpTarget,jdbcType=VARCHAR},#{ebuyProductDetail,jdbcType=VARCHAR},sysdate(),str_to_date(#{sys0UpdTime,jdbcType=DATE},'%Y-%m-%d %T'),str_to_date(#{sys0DelTime,jdbcType=DATE},'%Y-%m-%d %T'),#{sys0AddUser},#{sys0UpdUser},#{sys0DelUser},0)
	 </sql>
    <insert id="insert_messageToBeSend" parameterType="MessageToBeSend">
		<include refid="messageToBeSendBase.insert_messageToBeSend"/>
    </insert>
    
	<!-- 批量新增(待发送短信或待推送消息)信息 -->
    <insert id="insert_messageToBeSend_Batch" parameterType="java.util.List">
    	INSERT INTO t_message_to_be_send 
		(f_id,f_msg_type,f_title,f_content,f_send_range,f_send_time,f_send_status,f_operator_user,f_send_count,f_short_url,f_white_list,f_black_list,f_jump_target,f_ebuy_product_detail,f_sys0_add_time,f_sys0_upd_time,f_sys0_del_time,f_sys0_add_user,f_sys0_upd_user,f_sys0_del_user,f_sys0_del_state) VALUES  
		<foreach item="item" collection="list"  separator=","><!-- open="("  close=")" -->
		(#{item.id},#{item.msgType},#{item.title,jdbcType=VARCHAR},#{item.content,jdbcType=VARCHAR},#{item.sendRange},str_to_date(#{item.sendTime,jdbcType=DATE},'%Y-%m-%d %T'),#{item.sendStatus},#{item.operatorUser,jdbcType=VARCHAR},#{item.sendCount},#{item.shortUrl,jdbcType=VARCHAR},#{item.whiteList,jdbcType=VARCHAR},#{item.blackList,jdbcType=VARCHAR},#{item.jumpTarget,jdbcType=VARCHAR},#{item.ebuyProductDetail,jdbcType=VARCHAR},sysdate(),str_to_date(#{item.sys0UpdTime,jdbcType=DATE},'%Y-%m-%d %T'),str_to_date(#{item.sys0DelTime,jdbcType=DATE},'%Y-%m-%d %T'),#{item.sys0AddUser},#{item.sys0UpdUser},#{item.sys0DelUser},0)
		</foreach>
    </insert>
    
    <!-- 更新(待发送短信或待推送消息)信息。 -->
    <sql id="update_messageToBeSend">
		UPDATE t_message_to_be_send		<trim prefix="SET" prefixOverrides=","> 		<if test="msgType != null and !msgType.equals('') "> ,f_msg_type=#{msgType}</if> 		<if test="title != null and !title.equals('') "> ,f_title=#{title}</if> 		<if test="content != null and !content.equals('') "> ,f_content=#{content}</if> 		<if test="sendRange != null and !sendRange.equals('') "> ,f_send_range=#{sendRange}</if> 		<if test="sendTime != null and !sendTime.equals('') "> ,f_send_time=str_to_date(#{sendTime},'%Y-%m-%d %T')</if> 		<if test="sendStatus != null and !sendStatus.equals('') "> ,f_send_status=#{sendStatus}</if> 		<if test="operatorUser != null and !operatorUser.equals('') "> ,f_operator_user=#{operatorUser}</if> 		<if test="sendCount != null and !sendCount.equals('') "> ,f_send_count=#{sendCount}</if> 		<if test="shortUrl != null and !shortUrl.equals('') "> ,f_short_url=#{shortUrl}</if> 		<if test="whiteList != null and !whiteList.equals('') "> ,f_white_list=#{whiteList}</if> 		<if test="blackList != null and !blackList.equals('') "> ,f_black_list=#{blackList}</if> 		<if test="jumpTarget != null and !jumpTarget.equals('') "> ,f_jump_target=#{jumpTarget}</if> 		<if test="ebuyProductDetail != null and !ebuyProductDetail.equals('') "> ,f_ebuy_product_detail=#{ebuyProductDetail}</if> 		<if test="sys0AddTime != null and !sys0AddTime.equals('') "> ,f_sys0_add_time=str_to_date(#{sys0AddTime},'%Y-%m-%d %T')</if> 		<if test="sys0UpdTime != null and !sys0UpdTime.equals('') "> ,f_sys0_upd_time=str_to_date(#{sys0UpdTime},'%Y-%m-%d %T')</if> 		<if test="sys0UpdTime == null or sys0UpdTime.equals('')  "> ,f_sys0_upd_time= sysdate() </if> 		<if test="sys0DelTime != null and !sys0DelTime.equals('') "> ,f_sys0_del_time=str_to_date(#{sys0DelTime},'%Y-%m-%d %T')</if> 		<if test="sys0AddUser != null and !sys0AddUser.equals('') "> ,f_sys0_add_user=#{sys0AddUser}</if> 		<if test="sys0UpdUser != null and !sys0UpdUser.equals('') "> ,f_sys0_upd_user=#{sys0UpdUser}</if> 		<if test="sys0DelUser != null and !sys0DelUser.equals('') "> ,f_sys0_del_user=#{sys0DelUser}</if> 		<if test="sys0DelState != null and !sys0DelState.equals('') "> ,f_sys0_del_state=#{sys0DelState}</if>		</trim>		WHERE f_id=#{id}
    </sql>
	<update id="update_messageToBeSend" parameterType="MessageToBeSend">
		<include refid="messageToBeSendBase.update_messageToBeSend"/>
    </update>
    
    <!-- 批量更新(待发送短信或待推送消息)信息。 -->
    <update id="update_messageToBeSend_Batch" parameterType="java.util.List">
    	<foreach collection="list" item="item" index="index" separator=";" open="" close="">
		UPDATE t_message_to_be_send		<trim prefix="SET" prefixOverrides=","> 		<if test="item.msgType != null and !item.msgType.equals('')  "> ,f_msg_type=#{item.msgType}</if> 		<if test="item.title != null and !item.title.equals('')  "> ,f_title=#{item.title}</if> 		<if test="item.content != null and !item.content.equals('')  "> ,f_content=#{item.content}</if> 		<if test="item.sendRange != null and !item.sendRange.equals('')  "> ,f_send_range=#{item.sendRange}</if> 		<if test="item.sendTime != null and !item.sendTime.equals('')  "> ,f_send_time=str_to_date(#{item.sendTime},'%Y-%m-%d %T')</if> 		<if test="item.sendStatus != null and !item.sendStatus.equals('')  "> ,f_send_status=#{item.sendStatus}</if> 		<if test="item.operatorUser != null and !item.operatorUser.equals('')  "> ,f_operator_user=#{item.operatorUser}</if> 		<if test="item.sendCount != null and !item.sendCount.equals('')  "> ,f_send_count=#{item.sendCount}</if> 		<if test="item.shortUrl != null and !item.shortUrl.equals('')  "> ,f_short_url=#{item.shortUrl}</if> 		<if test="item.whiteList != null and !item.whiteList.equals('')  "> ,f_white_list=#{item.whiteList}</if> 		<if test="item.blackList != null and !item.blackList.equals('')  "> ,f_black_list=#{item.blackList}</if> 		<if test="item.jumpTarget != null and !item.jumpTarget.equals('')  "> ,f_jump_target=#{item.jumpTarget}</if> 		<if test="item.ebuyProductDetail != null and !item.ebuyProductDetail.equals('')  "> ,f_ebuy_product_detail=#{item.ebuyProductDetail}</if> 		<if test="item.sys0AddTime != null and !item.sys0AddTime.equals('')  "> ,f_sys0_add_time=str_to_date(#{item.sys0AddTime},'%Y-%m-%d %T')</if> 		<if test="item.sys0UpdTime != null and !item.sys0UpdTime.equals('')  "> ,f_sys0_upd_time=str_to_date(#{item.sys0UpdTime},'%Y-%m-%d %T')</if> 		<if test="item.sys0UpdTime == null or item.sys0UpdTime == '' "> ,f_sys0_upd_time= sysdate() </if> 		<if test="item.sys0DelTime != null and !item.sys0DelTime.equals('')  "> ,f_sys0_del_time=str_to_date(#{item.sys0DelTime},'%Y-%m-%d %T')</if> 		<if test="item.sys0AddUser != null and !item.sys0AddUser.equals('')  "> ,f_sys0_add_user=#{item.sys0AddUser}</if> 		<if test="item.sys0UpdUser != null and !item.sys0UpdUser.equals('')  "> ,f_sys0_upd_user=#{item.sys0UpdUser}</if> 		<if test="item.sys0DelUser != null and !item.sys0DelUser.equals('')  "> ,f_sys0_del_user=#{item.sys0DelUser}</if> 		<if test="item.sys0DelState != null and !item.sys0DelState.equals('')  "> ,f_sys0_del_state=#{item.sys0DelState}</if>		</trim>		WHERE f_id=#{item.id}
    	</foreach>
    </update>

   <!-- 根据序列号删除(待发送短信或待推送消息)信息_逻辑删除。 -->
    <sql id="delete_messageToBeSend_Logic">
		UPDATE t_message_to_be_send		<trim prefix="SET" prefixOverrides=","> 		<if test="msgType != null and !msgType.equals('')  "> ,f_msg_type=#{msgType}</if> 		<if test="title != null and !title.equals('')  "> ,f_title=#{title}</if> 		<if test="content != null and !content.equals('')  "> ,f_content=#{content}</if> 		<if test="sendRange != null and !sendRange.equals('')  "> ,f_send_range=#{sendRange}</if> 		<if test="sendTime != null and !sendTime.equals('')  "> ,f_send_time=str_to_date(#{sendTime},'%Y-%m-%d %T')</if> 		<if test="sendStatus != null and !sendStatus.equals('')  "> ,f_send_status=#{sendStatus}</if> 		<if test="operatorUser != null and !operatorUser.equals('')  "> ,f_operator_user=#{operatorUser}</if> 		<if test="sendCount != null and !sendCount.equals('')  "> ,f_send_count=#{sendCount}</if> 		<if test="shortUrl != null and !shortUrl.equals('')  "> ,f_short_url=#{shortUrl}</if> 		<if test="whiteList != null and !whiteList.equals('')  "> ,f_white_list=#{whiteList}</if> 		<if test="blackList != null and !blackList.equals('')  "> ,f_black_list=#{blackList}</if> 		<if test="jumpTarget != null and !jumpTarget.equals('')  "> ,f_jump_target=#{jumpTarget}</if> 		<if test="ebuyProductDetail != null and !ebuyProductDetail.equals('')  "> ,f_ebuy_product_detail=#{ebuyProductDetail}</if> 		<if test="sys0AddTime != null and !sys0AddTime.equals('')  "> ,f_sys0_add_time=str_to_date(#{sys0AddTime},'%Y-%m-%d %T')</if> 		<if test="sys0UpdTime != null and !sys0UpdTime.equals('')  "> ,f_sys0_upd_time=str_to_date(#{sys0UpdTime},'%Y-%m-%d %T')</if> 		<if test="sys0DelTime != null and !sys0DelTime.equals('')  "> ,f_sys0_del_time=str_to_date(#{sys0DelTime},'%Y-%m-%d %T')</if> 		<if test="sys0DelTime == null or sys0DelTime == '' "> ,f_sys0_del_time= sysdate() </if> 		<if test="sys0AddUser != null and !sys0AddUser.equals('')  "> ,f_sys0_add_user=#{sys0AddUser}</if> 		<if test="sys0UpdUser != null and !sys0UpdUser.equals('')  "> ,f_sys0_upd_user=#{sys0UpdUser}</if> 		<if test="sys0DelUser != null and !sys0DelUser.equals('')  "> ,f_sys0_del_user=#{sys0DelUser}</if> 		,f_sys0_del_state= 1 		</trim>		WHERE 1=1  		AND f_sys0_del_state = 0 		AND f_id=#{id}
    </sql>
    <update id="delete_messageToBeSend_Logic" parameterType="MessageToBeSend">
		<include refid="messageToBeSendBase.delete_messageToBeSend_Logic"/>
    </update>
    
    <!-- 批量删除(待发送短信或待推送消息)信息_逻辑删除 -->
    <update id="delete_messageToBeSend_Logic_Batch" parameterType="java.util.List">
		<foreach collection="list" item="item" index="index" separator=";" open="" close="">
		UPDATE t_message_to_be_send		<trim prefix="SET" prefixOverrides=","> 		<if test="item.msgType != null and !item.msgType.equals('')  "> ,f_msg_type=#{item.msgType}</if> 		<if test="item.title != null and !item.title.equals('')  "> ,f_title=#{item.title}</if> 		<if test="item.content != null and !item.content.equals('')  "> ,f_content=#{item.content}</if> 		<if test="item.sendRange != null and !item.sendRange.equals('')  "> ,f_send_range=#{item.sendRange}</if> 		<if test="item.sendTime != null and !item.sendTime.equals('')  "> ,f_send_time=str_to_date(#{item.sendTime},'%Y-%m-%d %T')</if> 		<if test="item.sendStatus != null and !item.sendStatus.equals('')  "> ,f_send_status=#{item.sendStatus}</if> 		<if test="item.operatorUser != null and !item.operatorUser.equals('')  "> ,f_operator_user=#{item.operatorUser}</if> 		<if test="item.sendCount != null and !item.sendCount.equals('')  "> ,f_send_count=#{item.sendCount}</if> 		<if test="item.shortUrl != null and !item.shortUrl.equals('')  "> ,f_short_url=#{item.shortUrl}</if> 		<if test="item.whiteList != null and !item.whiteList.equals('')  "> ,f_white_list=#{item.whiteList}</if> 		<if test="item.blackList != null and !item.blackList.equals('')  "> ,f_black_list=#{item.blackList}</if> 		<if test="item.jumpTarget != null and !item.jumpTarget.equals('')  "> ,f_jump_target=#{item.jumpTarget}</if> 		<if test="item.ebuyProductDetail != null and !item.ebuyProductDetail.equals('')  "> ,f_ebuy_product_detail=#{item.ebuyProductDetail}</if> 		<if test="item.sys0AddTime != null and !item.sys0AddTime.equals('')  "> ,f_sys0_add_time=str_to_date(#{item.sys0AddTime},'%Y-%m-%d %T')</if> 		<if test="item.sys0UpdTime != null and !item.sys0UpdTime.equals('')  "> ,f_sys0_upd_time=str_to_date(#{item.sys0UpdTime},'%Y-%m-%d %T')</if> 		<if test="item.sys0DelTime != null and !item.sys0DelTime.equals('')  "> ,f_sys0_del_time=str_to_date(#{item.sys0DelTime},'%Y-%m-%d %T')</if> 		<if test="item.sys0DelTime == null or item.sys0DelTime == '' "> ,f_sys0_del_time= sysdate() </if> 		<if test="item.sys0AddUser != null and !item.sys0AddUser.equals('')  "> ,f_sys0_add_user=#{item.sys0AddUser}</if> 		<if test="item.sys0UpdUser != null and !item.sys0UpdUser.equals('')  "> ,f_sys0_upd_user=#{item.sys0UpdUser}</if> 		<if test="item.sys0DelUser != null and !item.sys0DelUser.equals('')  "> ,f_sys0_del_user=#{item.sys0DelUser}</if> 		,f_sys0_del_state= 1 		</trim>		WHERE 1=1  		AND f_sys0_del_state = 0 		AND f_id=#{item.id}
    	</foreach>
    </update>
    
    <!-- 根据序列号删除(待发送短信或待推送消息)信息。 -->
    <sql id="delete_messageToBeSend">
		DELETE FROM t_message_to_be_send WHERE f_id=#{_parameter}
    </sql>
    <delete id="delete_messageToBeSend" parameterType="java.lang.String">
		<include refid="messageToBeSendBase.delete_messageToBeSend"/>
    </delete>
    
    <!-- 根据序列号批量删除(待发送短信或待推送消息)信息。 -->
    <delete id="delete_messageToBeSend_Batch" parameterType="java.util.List">
		DELETE FROM t_message_to_be_send WHERE 1=1 AND f_id IN 
		<foreach item="item" collection="list" open="(" separator="," close=")">
			#{item}
		</foreach>
    </delete>
    
</mapper>
