<?xml version="1.0" encoding="UTF-8"?><!DOCTYPE mapper PUBLIC "-//mybatis.org//DTD Mapper 3.0//EN" "http://mybatis.org/dtd/mybatis-3-mapper.dtd"><!-- tblNameCN:用户所持消费券表 t_user_coupon --><mapper namespace="userCouponBase">	<resultMap type="UserCoupon" id="userCouponBaseMap">        <id column="f_id" javaType="java.math.BigInteger" property="id"/>  <!--  -->        <result column="t_user_f_id" javaType="java.math.BigInteger" property="tUserFId"/>  <!-- 消费券拥有者ID -->        <result column="t_coupon_f_id" javaType="java.math.BigInteger" property="tCouponFId"/>  <!-- 消费券ID -->        <result column="t_ebuy_order_f_id" javaType="java.math.BigInteger" property="tEbuyOrderFId"/>  <!-- 来源订单ID -->        <result column="f_use_start_date" javaType="java.lang.String" property="useStartDate"/>  <!-- 可用开始时间 -->        <result column="f_use_end_date" javaType="java.lang.String" property="useEndDate"/>  <!-- 可用结束时间 -->        <result column="f_status" javaType="java.lang.Integer" property="status"/>  <!-- 消费券状态 -->        <result column="f_get_type" javaType="java.lang.Integer" property="getType"/>  <!-- 消费券获取方式 -->        <result column="f_sys0_add_time" javaType="java.lang.String" property="sys0AddTime"/>  <!-- 新增时间 -->        <result column="f_sys0_upd_time" javaType="java.lang.String" property="sys0UpdTime"/>  <!-- 更新时间 -->        <result column="f_sys0_add_user" javaType="java.math.BigInteger" property="sys0AddUser"/>  <!--  -->        <result column="f_sys0_upd_user" javaType="java.math.BigInteger" property="sys0UpdUser"/>  <!--  -->        <result column="f_sys0_del_user" javaType="java.math.BigInteger" property="sys0DelUser"/>  <!--  -->        <result column="f_sys0_del_state" javaType="java.lang.Integer" property="sys0DelState"/>  <!--  -->        <result column="f_sys0_del_time" javaType="java.lang.String" property="sys0DelTime"/>  <!--  -->	</resultMap>	<resultMap type="UserCoupon" id="userCouponExtendMap" extends="userCouponBaseMap">	</resultMap>	<resultMap type="UserCoupon" id="userCouponBaseMap_AppendTable">        <id column="UCid" javaType="java.math.BigInteger" property="id"/>  <!--  -->        <result column="UCtUserFId" javaType="java.math.BigInteger" property="tUserFId"/>  <!-- 消费券拥有者ID -->        <result column="UCtCouponFId" javaType="java.math.BigInteger" property="tCouponFId"/>  <!-- 消费券ID -->        <result column="UCtEbuyOrderFId" javaType="java.math.BigInteger" property="tEbuyOrderFId"/>  <!-- 来源订单ID -->        <result column="UCuseStartDate" javaType="java.lang.String" property="useStartDate"/>  <!-- 可用开始时间 -->        <result column="UCuseEndDate" javaType="java.lang.String" property="useEndDate"/>  <!-- 可用结束时间 -->        <result column="UCstatus" javaType="java.lang.Integer" property="status"/>  <!-- 消费券状态 -->        <result column="UCgetType" javaType="java.lang.Integer" property="getType"/>  <!-- 消费券获取方式 -->        <result column="UCsys0AddTime" javaType="java.lang.String" property="sys0AddTime"/>  <!-- 新增时间 -->        <result column="UCsys0UpdTime" javaType="java.lang.String" property="sys0UpdTime"/>  <!-- 更新时间 -->        <result column="UCsys0AddUser" javaType="java.math.BigInteger" property="sys0AddUser"/>  <!--  -->        <result column="UCsys0UpdUser" javaType="java.math.BigInteger" property="sys0UpdUser"/>  <!--  -->        <result column="UCsys0DelUser" javaType="java.math.BigInteger" property="sys0DelUser"/>  <!--  -->        <result column="UCsys0DelState" javaType="java.lang.Integer" property="sys0DelState"/>  <!--  -->        <result column="UCsys0DelTime" javaType="java.lang.String" property="sys0DelTime"/>  <!--  -->	</resultMap>	<resultMap type="UserCoupon" id="userCouponBaseMap_AppendTable1">        <id column="UC1id" javaType="java.math.BigInteger" property="id"/>  <!--  -->        <result column="UC1tUserFId" javaType="java.math.BigInteger" property="tUserFId"/>  <!-- 消费券拥有者ID -->        <result column="UC1tCouponFId" javaType="java.math.BigInteger" property="tCouponFId"/>  <!-- 消费券ID -->        <result column="UC1tEbuyOrderFId" javaType="java.math.BigInteger" property="tEbuyOrderFId"/>  <!-- 来源订单ID -->        <result column="UC1useStartDate" javaType="java.lang.String" property="useStartDate"/>  <!-- 可用开始时间 -->        <result column="UC1useEndDate" javaType="java.lang.String" property="useEndDate"/>  <!-- 可用结束时间 -->        <result column="UC1status" javaType="java.lang.Integer" property="status"/>  <!-- 消费券状态 -->        <result column="UC1getType" javaType="java.lang.Integer" property="getType"/>  <!-- 消费券获取方式 -->        <result column="UC1sys0AddTime" javaType="java.lang.String" property="sys0AddTime"/>  <!-- 新增时间 -->        <result column="UC1sys0UpdTime" javaType="java.lang.String" property="sys0UpdTime"/>  <!-- 更新时间 -->        <result column="UC1sys0AddUser" javaType="java.math.BigInteger" property="sys0AddUser"/>  <!--  -->        <result column="UC1sys0UpdUser" javaType="java.math.BigInteger" property="sys0UpdUser"/>  <!--  -->        <result column="UC1sys0DelUser" javaType="java.math.BigInteger" property="sys0DelUser"/>  <!--  -->        <result column="UC1sys0DelState" javaType="java.lang.Integer" property="sys0DelState"/>  <!--  -->        <result column="UC1sys0DelTime" javaType="java.lang.String" property="sys0DelTime"/>  <!--  -->	</resultMap>	<!-- 公共sql提取  -->	<sql id="queryHead">		UC.f_id,UC.t_user_f_id,UC.t_coupon_f_id,UC.t_ebuy_order_f_id,date_format(UC.f_use_start_date,'%Y-%m-%d %T') as f_use_start_date,date_format(UC.f_use_end_date,'%Y-%m-%d %T') as f_use_end_date,UC.f_status, UC.f_get_type	</sql>	<sql id="queryHead_AppendTable">		UC.f_id as UCid,UC.t_user_f_id as UCtUserFId,UC.t_coupon_f_id as UCtCouponFId,UC.t_ebuy_order_f_id as UCtEbuyOrderFId,date_format(UC.f_use_start_date,'%Y-%m-%d %T') as UCuseStartDate,date_format(UC.f_use_end_date,'%Y-%m-%d %T') as UCuseEndDate,UC.f_status as UCstatus, UC.f_get_type as UCgetType	</sql>	<sql id="queryHead_AppendTable1">		UC1.f_id as UC1id,UC1.t_user_f_id as UC1tUserFId,UC1.t_coupon_f_id as UC1tCouponFId,UC1.t_ebuy_order_f_id as UC1tEbuyOrderFId,date_format(UC1.f_use_start_date,'%Y-%m-%d %T') as UC1useStartDate,date_format(UC1.f_use_end_date,'%Y-%m-%d %T') as UC1useEndDate,UC1.f_status as UC1status, UC1.f_get_type UC1getType	</sql>	<sql id="querySql">        <if test="id != null">  and (UC.f_id = #{id} ) </if>        <if test="tUserFId != null">  and (UC.t_user_f_id = #{tUserFId} ) </if>        <if test="tCouponFId != null">  and (UC.t_coupon_f_id = #{tCouponFId} ) </if>        <if test="tEbuyOrderFId != null">  and (UC.t_ebuy_order_f_id = #{tEbuyOrderFId} ) </if>        <if test="useStartDate != null and !useStartDate.equals('')  ">  and (UC.f_use_start_date = str_to_date(#{useStartDate},'%Y-%m-%d %T') ) </if>        <if test="useStartDate_START != null and !useStartDate_START.equals('')  ">              <![CDATA[ and (UC.f_use_start_date >= str_to_date(#{useStartDate_START},'%Y-%m-%d %T') ) ]]>        </if>        <if test="useStartDate_END != null and !useStartDate_END.equals('')  ">            <![CDATA[ and (UC.f_use_start_date <= str_to_date(#{useStartDate_END},'%Y-%m-%d %T') ) ]]>        </if>        <if test="useEndDate != null and !useEndDate.equals('')  ">  and (UC.f_use_end_date = str_to_date(#{useEndDate},'%Y-%m-%d %T') ) </if>        <if test="useEndDate_START != null and !useEndDate_START.equals('')  ">              <![CDATA[ and (UC.f_use_end_date >= str_to_date(#{useEndDate_START},'%Y-%m-%d %T') ) ]]>        </if>        <if test="useEndDate_END != null and !useEndDate_END.equals('')  ">            <![CDATA[ and (UC.f_use_end_date <= str_to_date(#{useEndDate_END},'%Y-%m-%d %T') ) ]]>        </if>        <if test="status != null">  and (UC.f_status = #{status} ) </if>        <if test="getType != null">  and (UC.f_getType = #{getType} ) </if>        <if test="sys0AddTime != null and !sys0AddTime.equals('')  ">  and (UC.f_sys0_add_time = str_to_date(#{sys0AddTime},'%Y-%m-%d %T') ) </if>        <if test="sys0AddTime_START != null and !sys0AddTime_START.equals('')  ">              <![CDATA[ and (UC.f_sys0_add_time >= str_to_date(#{sys0AddTime_START},'%Y-%m-%d %T') ) ]]>        </if>        <if test="sys0AddTime_END != null and !sys0AddTime_END.equals('')  ">            <![CDATA[ and (UC.f_sys0_add_time <= str_to_date(#{sys0AddTime_END},'%Y-%m-%d %T') ) ]]>        </if>        <if test="sys0UpdTime != null and !sys0UpdTime.equals('')  ">  and (UC.f_sys0_upd_time = str_to_date(#{sys0UpdTime},'%Y-%m-%d %T') ) </if>        <if test="sys0UpdTime_START != null and !sys0UpdTime_START.equals('')  ">              <![CDATA[ and (UC.f_sys0_upd_time >= str_to_date(#{sys0UpdTime_START},'%Y-%m-%d %T') ) ]]>        </if>        <if test="sys0UpdTime_END != null and !sys0UpdTime_END.equals('')  ">            <![CDATA[ and (UC.f_sys0_upd_time <= str_to_date(#{sys0UpdTime_END},'%Y-%m-%d %T') ) ]]>        </if>        <if test="sys0AddUser != null">  and (UC.f_sys0_add_user = #{sys0AddUser} ) </if>        <if test="sys0UpdUser != null">  and (UC.f_sys0_upd_user = #{sys0UpdUser} ) </if>        <if test="sys0DelUser != null">  and (UC.f_sys0_del_user = #{sys0DelUser} ) </if>        <if test="sys0DelState != null">  and (UC.f_sys0_del_state = #{sys0DelState} ) </if>        <if test="sys0DelState == null">  and (UC.f_sys0_del_state = 0 ) </if>        <if test="sys0DelTime != null and !sys0DelTime.equals('')  ">  and (UC.f_sys0_del_time = str_to_date(#{sys0DelTime},'%Y-%m-%d %T') ) </if>        <if test="sys0DelTime_START != null and !sys0DelTime_START.equals('')  ">              <![CDATA[ and (UC.f_sys0_del_time >= str_to_date(#{sys0DelTime_START},'%Y-%m-%d %T') ) ]]>        </if>        <if test="sys0DelTime_END != null and !sys0DelTime_END.equals('')  ">            <![CDATA[ and (UC.f_sys0_del_time <= str_to_date(#{sys0DelTime_END},'%Y-%m-%d %T') ) ]]>        </if>	</sql>	<sql id="querySqlDim">        <if test="id != null and !id.equals('')  ">  and (UC.f_id = #{id} ) </if>        <if test="tUserFId != null and !tUserFId.equals('')  ">  and (UC.t_user_f_id = #{tUserFId} ) </if>        <if test="tCouponFId != null and !tCouponFId.equals('')  ">  and (UC.t_coupon_f_id = #{tCouponFId} ) </if>        <if test="tEbuyOrderFId != null and !tEbuyOrderFId.equals('')  ">  and (UC.t_ebuy_order_f_id = #{tEbuyOrderFId} ) </if>        <if test="useStartDate != null and !useStartDate.equals('')  ">  and (UC.f_use_start_date = str_to_date(#{useStartDate},'%Y-%m-%d %T') ) </if>        <if test="useStartDate_START != null and !useStartDate_START.equals('')  ">              <![CDATA[ and (UC.f_use_start_date >= str_to_date(#{useStartDate_START},'%Y-%m-%d %T') ) ]]>        </if>        <if test="useStartDate_END != null and !useStartDate_END.equals('')  ">            <![CDATA[ and (UC.f_use_start_date <= str_to_date(#{useStartDate_END},'%Y-%m-%d %T') ) ]]>        </if>        <if test="useEndDate != null and !useEndDate.equals('')  ">  and (UC.f_use_end_date = str_to_date(#{useEndDate},'%Y-%m-%d %T') ) </if>        <if test="useEndDate_START != null and !useEndDate_START.equals('')  ">              <![CDATA[ and (UC.f_use_end_date >= str_to_date(#{useEndDate_START},'%Y-%m-%d %T') ) ]]>        </if>        <if test="useEndDate_END != null and !useEndDate_END.equals('')  ">            <![CDATA[ and (UC.f_use_end_date <= str_to_date(#{useEndDate_END},'%Y-%m-%d %T') ) ]]>        </if>        <if test="status != null and !status.equals('')  ">  and (UC.f_status = #{status} ) </if>        <if test="getType != null and !getType.equals('')  ">  and (UC.f_getType = #{getType} ) </if>        <if test="sys0AddTime != null and !sys0AddTime.equals('')  ">  and (UC.f_sys0_add_time = str_to_date(#{sys0AddTime},'%Y-%m-%d %T') ) </if>        <if test="sys0AddTime_START != null and !sys0AddTime_START.equals('')  ">              <![CDATA[ and (UC.f_sys0_add_time >= str_to_date(#{sys0AddTime_START},'%Y-%m-%d %T') ) ]]>        </if>        <if test="sys0AddTime_END != null and !sys0AddTime_END.equals('')  ">            <![CDATA[ and (UC.f_sys0_add_time <= str_to_date(#{sys0AddTime_END},'%Y-%m-%d %T') ) ]]>        </if>        <if test="sys0UpdTime != null and !sys0UpdTime.equals('')  ">  and (UC.f_sys0_upd_time = str_to_date(#{sys0UpdTime},'%Y-%m-%d %T') ) </if>        <if test="sys0UpdTime_START != null and !sys0UpdTime_START.equals('')  ">              <![CDATA[ and (UC.f_sys0_upd_time >= str_to_date(#{sys0UpdTime_START},'%Y-%m-%d %T') ) ]]>        </if>        <if test="sys0UpdTime_END != null and !sys0UpdTime_END.equals('')  ">            <![CDATA[ and (UC.f_sys0_upd_time <= str_to_date(#{sys0UpdTime_END},'%Y-%m-%d %T') ) ]]>        </if>        <if test="sys0AddUser != null and !sys0AddUser.equals('')  ">  and (UC.f_sys0_add_user = #{sys0AddUser} ) </if>        <if test="sys0UpdUser != null and !sys0UpdUser.equals('')  ">  and (UC.f_sys0_upd_user = #{sys0UpdUser} ) </if>        <if test="sys0DelUser != null and !sys0DelUser.equals('')  ">  and (UC.f_sys0_del_user = #{sys0DelUser} ) </if>        <if test="sys0DelState != null and !sys0DelState.equals('')  ">  and (UC.f_sys0_del_state = #{sys0DelState} ) </if>        <if test="sys0DelState == null or sys0DelState == '' ">  and (UC.f_sys0_del_state = 0 ) </if>        <if test="sys0DelTime != null and !sys0DelTime.equals('')  ">  and (UC.f_sys0_del_time = str_to_date(#{sys0DelTime},'%Y-%m-%d %T') ) </if>        <if test="sys0DelTime_START != null and !sys0DelTime_START.equals('')  ">              <![CDATA[ and (UC.f_sys0_del_time >= str_to_date(#{sys0DelTime_START},'%Y-%m-%d %T') ) ]]>        </if>        <if test="sys0DelTime_END != null and !sys0DelTime_END.equals('')  ">            <![CDATA[ and (UC.f_sys0_del_time <= str_to_date(#{sys0DelTime_END},'%Y-%m-%d %T') ) ]]>        </if>	</sql>	<sql id="dimCheckSql">		<if test="_QUERY_TYPE_IF_DIM == true"><include refid="userCouponBase.querySqlDim"/></if>		<if test="_QUERY_TYPE_IF_DIM == null or  _QUERY_TYPE_IF_DIM == '' or  _QUERY_TYPE_IF_DIM == false or _QUERY_TYPE_IF_DIM != true"><include refid="userCouponBase.querySql"/></if><!-- 默认精确查询 -->		<!-- <if test="_QUERY_TYPE_IF_DIM != true"><include refid="userCouponBase.querySql"/></if> --><!-- 默认精确查询 -->	</sql>	<!-- 各种查询附加的查询条件 -->	<sql id="busiQueryCondition">	    <include refid="userCouponBase.busiQueryCount"/>	</sql>	<!-- 查询记录数附加的查询条件 -->	<sql id="busiQueryCount">	     FROM t_user_coupon UC    	 WHERE 1=1	</sql>		<!-- 根据条件查询(用户所持消费券表)信息。 -->	<sql id="select_userCoupon">		SELECT <include refid="userCouponBase.queryHead"/>		<include refid="userCouponBase.busiQueryCondition"/>		<include refid="userCouponBase.dimCheckSql"/>		ORDER BY UC.f_id DESC	</sql>	<select id="select_userCoupon" parameterType="java.util.Map" resultMap="userCouponBase.userCouponExtendMap">		<include refid="userCouponBase.select_userCoupon"/>	</select>		<!-- 根据条件分页查询(用户所持消费券表)信息  -->	<sql id="select_userCoupon_withPage">		SELECT <include refid="userCouponBase.queryHead"/>		<include refid="userCouponBase.busiQueryCondition"/>		<include refid="userCouponBase.dimCheckSql"/>		ORDER BY f_id DESC		<![CDATA[ LIMIT #{_begin},#{_length} ]]>	</sql>	<select id="select_userCoupon_withPage" resultMap="userCouponBase.userCouponExtendMap" parameterType="java.util.Map">		<include refid="userCouponBase.select_userCoupon_withPage"/>	</select>	<!-- 根据序列号查询某个(用户所持消费券表)信息。 -->	<sql id="select_userCoupon_bySeqId">		SELECT <include refid="userCouponBase.queryHead"/>		<include refid="userCouponBase.busiQueryCondition"/>		 and UC.f_id = #{_parameter}	</sql>	<select id="select_userCoupon_bySeqId" parameterType="java.math.BigInteger" resultMap="userCouponBase.userCouponBaseMap">		<include refid="userCouponBase.select_userCoupon_bySeqId"/>	</select>		<!-- 根据条件查询满足条件的(用户所持消费券表)记录数  -->	<sql id="select_userCoupon_count">		SELECT COUNT(*)		<include refid="userCouponBase.busiQueryCount"/>		<include refid="userCouponBase.dimCheckSql"/>	</sql>	<select id="select_userCoupon_count" resultType="java.lang.Integer">		<include refid="userCouponBase.select_userCoupon_count"/>	</select>		 <!-- 往(用户所持消费券表)新增一条记录。 -->	 <sql id="insert_userCoupon">		INSERT INTO t_user_coupon 		(f_id,t_user_f_id,t_coupon_f_id,t_ebuy_order_f_id,f_use_start_date,f_use_end_date,f_status,f_get_type,f_sys0_add_time,f_sys0_upd_time,f_sys0_add_user,f_sys0_upd_user,f_sys0_del_user,f_sys0_del_state,f_sys0_del_time) VALUES		(#{id},#{tUserFId},#{tCouponFId},#{tEbuyOrderFId},str_to_date(#{useStartDate,jdbcType=DATE},'%Y-%m-%d %T'),str_to_date(#{useEndDate,jdbcType=DATE},'%Y-%m-%d %T'),#{status},#{getType},sysdate(),str_to_date(#{sys0UpdTime,jdbcType=DATE},'%Y-%m-%d %T'),#{sys0AddUser},#{sys0UpdUser},#{sys0DelUser},0,str_to_date(#{sys0DelTime,jdbcType=DATE},'%Y-%m-%d %T'))	 </sql>    <insert id="insert_userCoupon" parameterType="UserCoupon">		<include refid="userCouponBase.insert_userCoupon"/>    </insert>    	<!-- 批量新增(用户所持消费券表)信息 -->    <insert id="insert_userCoupon_Batch" parameterType="java.util.List">    	INSERT INTO t_user_coupon 		(f_id,t_user_f_id,t_coupon_f_id,t_ebuy_order_f_id,f_use_start_date,f_use_end_date,f_status,f_get_type,f_sys0_add_time,f_sys0_upd_time,f_sys0_add_user,f_sys0_upd_user,f_sys0_del_user,f_sys0_del_state,f_sys0_del_time) VALUES		<foreach item="item" collection="list"  separator=","><!-- open="("  close=")" -->		(#{item.id},#{item.tUserFId},#{item.tCouponFId},#{item.tEbuyOrderFId},str_to_date(#{item.useStartDate,jdbcType=DATE},'%Y-%m-%d %T'),str_to_date(#{item.useEndDate,jdbcType=DATE},'%Y-%m-%d %T'),#{item.status},#{item.getType},sysdate(),str_to_date(#{item.sys0UpdTime,jdbcType=DATE},'%Y-%m-%d %T'),#{item.sys0AddUser},#{item.sys0UpdUser},#{item.sys0DelUser},0,str_to_date(#{item.sys0DelTime,jdbcType=DATE},'%Y-%m-%d %T'))		</foreach>    </insert>        <!-- 更新(用户所持消费券表)信息。 -->    <sql id="update_userCoupon">		UPDATE t_user_coupon		<trim prefix="SET" prefixOverrides=","> 		<if test="tUserFId != null and !tUserFId.equals('') "> ,t_user_f_id=#{tUserFId}</if> 		<if test="tCouponFId != null and !tCouponFId.equals('') "> ,t_coupon_f_id=#{tCouponFId}</if> 		<if test="tEbuyOrderFId != null and !tEbuyOrderFId.equals('') "> ,t_ebuy_order_f_id=#{tEbuyOrderFId}</if> 		<if test="useStartDate != null and !useStartDate.equals('') "> ,f_use_start_date=str_to_date(#{useStartDate},'%Y-%m-%d %T')</if> 		<if test="useEndDate != null and !useEndDate.equals('') "> ,f_use_end_date=str_to_date(#{useEndDate},'%Y-%m-%d %T')</if> 		<if test="status != null and !status.equals('') "> ,f_status=#{status}</if> 		<if test="getType != null and !getType.equals('') "> ,f_get_type=#{getType}</if> 		<if test="sys0AddTime != null and !sys0AddTime.equals('') "> ,f_sys0_add_time=str_to_date(#{sys0AddTime},'%Y-%m-%d %T')</if> 		<if test="sys0UpdTime != null and !sys0UpdTime.equals('') "> ,f_sys0_upd_time=str_to_date(#{sys0UpdTime},'%Y-%m-%d %T')</if> 		<if test="sys0UpdTime == null or sys0UpdTime.equals('')  "> ,f_sys0_upd_time= sysdate() </if> 		<if test="sys0AddUser != null and !sys0AddUser.equals('') "> ,f_sys0_add_user=#{sys0AddUser}</if> 		<if test="sys0UpdUser != null and !sys0UpdUser.equals('') "> ,f_sys0_upd_user=#{sys0UpdUser}</if> 		<if test="sys0DelUser != null and !sys0DelUser.equals('') "> ,f_sys0_del_user=#{sys0DelUser}</if> 		<if test="sys0DelState != null and !sys0DelState.equals('') "> ,f_sys0_del_state=#{sys0DelState}</if> 		<if test="sys0DelTime != null and !sys0DelTime.equals('') "> ,f_sys0_del_time=str_to_date(#{sys0DelTime},'%Y-%m-%d %T')</if>		</trim>		WHERE f_id=#{id}    </sql>	<update id="update_userCoupon" parameterType="UserCoupon">		<include refid="userCouponBase.update_userCoupon"/>    </update>        <!-- 批量更新(用户所持消费券表)信息。 -->    <update id="update_userCoupon_Batch" parameterType="java.util.List">    	<foreach collection="list" item="item" index="index" separator=";" open="" close="">		UPDATE t_user_coupon		<trim prefix="SET" prefixOverrides=","> 		<if test="item.tUserFId != null and !item.tUserFId.equals('')  "> ,t_user_f_id=#{item.tUserFId}</if> 		<if test="item.tCouponFId != null and !item.tCouponFId.equals('')  "> ,t_coupon_f_id=#{item.tCouponFId}</if> 		<if test="item.tEbuyOrderFId != null and !item.tEbuyOrderFId.equals('')  "> ,t_ebuy_order_f_id=#{item.tEbuyOrderFId}</if> 		<if test="item.useStartDate != null and !item.useStartDate.equals('')  "> ,f_use_start_date=str_to_date(#{item.useStartDate},'%Y-%m-%d %T')</if> 		<if test="item.useEndDate != null and !item.useEndDate.equals('')  "> ,f_use_end_date=str_to_date(#{item.useEndDate},'%Y-%m-%d %T')</if> 		<if test="item.status != null and !item.status.equals('')  "> ,f_status=#{item.status}</if> 		<if test="item.getType != null and !item.getType.equals('')  "> ,f_get_type=#{item.getType}</if> 		<if test="item.sys0AddTime != null and !item.sys0AddTime.equals('')  "> ,f_sys0_add_time=str_to_date(#{item.sys0AddTime},'%Y-%m-%d %T')</if> 		<if test="item.sys0UpdTime != null and !item.sys0UpdTime.equals('')  "> ,f_sys0_upd_time=str_to_date(#{item.sys0UpdTime},'%Y-%m-%d %T')</if> 		<if test="item.sys0UpdTime == null or item.sys0UpdTime == '' "> ,f_sys0_upd_time= sysdate() </if> 		<if test="item.sys0AddUser != null and !item.sys0AddUser.equals('')  "> ,f_sys0_add_user=#{item.sys0AddUser}</if> 		<if test="item.sys0UpdUser != null and !item.sys0UpdUser.equals('')  "> ,f_sys0_upd_user=#{item.sys0UpdUser}</if> 		<if test="item.sys0DelUser != null and !item.sys0DelUser.equals('')  "> ,f_sys0_del_user=#{item.sys0DelUser}</if> 		<if test="item.sys0DelState != null and !item.sys0DelState.equals('')  "> ,f_sys0_del_state=#{item.sys0DelState}</if> 		<if test="item.sys0DelTime != null and !item.sys0DelTime.equals('')  "> ,f_sys0_del_time=str_to_date(#{item.sys0DelTime},'%Y-%m-%d %T')</if>		</trim>		WHERE f_id=#{item.id}    	</foreach>    </update>   <!-- 根据序列号删除(用户所持消费券表)信息_逻辑删除。 -->    <sql id="delete_userCoupon_Logic">		UPDATE t_user_coupon		<trim prefix="SET" prefixOverrides=","> 		<if test="tUserFId != null and !tUserFId.equals('')  "> ,t_user_f_id=#{tUserFId}</if> 		<if test="tCouponFId != null and !tCouponFId.equals('')  "> ,t_coupon_f_id=#{tCouponFId}</if> 		<if test="tEbuyOrderFId != null and !tEbuyOrderFId.equals('')  "> ,t_ebuy_order_f_id=#{tEbuyOrderFId}</if> 		<if test="useStartDate != null and !useStartDate.equals('')  "> ,f_use_start_date=str_to_date(#{useStartDate},'%Y-%m-%d %T')</if> 		<if test="useEndDate != null and !useEndDate.equals('')  "> ,f_use_end_date=str_to_date(#{useEndDate},'%Y-%m-%d %T')</if> 		<if test="status != null and !status.equals('')  "> ,f_status=#{status}</if> 		<if test="getType != null and !getType.equals('')  "> ,f_get_type=#{getType}</if> 		<if test="sys0AddTime != null and !sys0AddTime.equals('')  "> ,f_sys0_add_time=str_to_date(#{sys0AddTime},'%Y-%m-%d %T')</if> 		<if test="sys0UpdTime != null and !sys0UpdTime.equals('')  "> ,f_sys0_upd_time=str_to_date(#{sys0UpdTime},'%Y-%m-%d %T')</if> 		<if test="sys0AddUser != null and !sys0AddUser.equals('')  "> ,f_sys0_add_user=#{sys0AddUser}</if> 		<if test="sys0UpdUser != null and !sys0UpdUser.equals('')  "> ,f_sys0_upd_user=#{sys0UpdUser}</if> 		<if test="sys0DelUser != null and !sys0DelUser.equals('')  "> ,f_sys0_del_user=#{sys0DelUser}</if> 		<if test="sys0DelTime != null and !sys0DelTime.equals('')  "> ,f_sys0_del_time=str_to_date(#{sys0DelTime},'%Y-%m-%d %T')</if> 		<if test="sys0DelTime == null or sys0DelTime == '' "> ,f_sys0_del_time= sysdate() </if> 		,f_sys0_del_state= 1 		</trim>		WHERE 1=1  		AND f_sys0_del_state = 0 		AND f_id=#{id}    </sql>    <update id="delete_userCoupon_Logic" parameterType="UserCoupon">		<include refid="userCouponBase.delete_userCoupon_Logic"/>    </update>        <!-- 批量删除(用户所持消费券表)信息_逻辑删除 -->    <update id="delete_userCoupon_Logic_Batch" parameterType="java.util.List">		<foreach collection="list" item="item" index="index" separator=";" open="" close="">		UPDATE t_user_coupon		<trim prefix="SET" prefixOverrides=","> 		<if test="item.tUserFId != null and !item.tUserFId.equals('')  "> ,t_user_f_id=#{item.tUserFId}</if> 		<if test="item.tCouponFId != null and !item.tCouponFId.equals('')  "> ,t_coupon_f_id=#{item.tCouponFId}</if> 		<if test="item.tEbuyOrderFId != null and !item.tEbuyOrderFId.equals('')  "> ,t_ebuy_order_f_id=#{item.tEbuyOrderFId}</if> 		<if test="item.useStartDate != null and !item.useStartDate.equals('')  "> ,f_use_start_date=str_to_date(#{item.useStartDate},'%Y-%m-%d %T')</if> 		<if test="item.useEndDate != null and !item.useEndDate.equals('')  "> ,f_use_end_date=str_to_date(#{item.useEndDate},'%Y-%m-%d %T')</if> 		<if test="item.status != null and !item.status.equals('')  "> ,f_status=#{item.status}</if> 		<if test="item.getType != null and !item.getType.equals('')  "> ,f_get_type=#{item.getType}</if> 		<if test="item.sys0AddTime != null and !item.sys0AddTime.equals('')  "> ,f_sys0_add_time=str_to_date(#{item.sys0AddTime},'%Y-%m-%d %T')</if> 		<if test="item.sys0UpdTime != null and !item.sys0UpdTime.equals('')  "> ,f_sys0_upd_time=str_to_date(#{item.sys0UpdTime},'%Y-%m-%d %T')</if> 		<if test="item.sys0AddUser != null and !item.sys0AddUser.equals('')  "> ,f_sys0_add_user=#{item.sys0AddUser}</if> 		<if test="item.sys0UpdUser != null and !item.sys0UpdUser.equals('')  "> ,f_sys0_upd_user=#{item.sys0UpdUser}</if> 		<if test="item.sys0DelUser != null and !item.sys0DelUser.equals('')  "> ,f_sys0_del_user=#{item.sys0DelUser}</if> 		<if test="item.sys0DelTime != null and !item.sys0DelTime.equals('')  "> ,f_sys0_del_time=str_to_date(#{item.sys0DelTime},'%Y-%m-%d %T')</if> 		<if test="item.sys0DelTime == null or item.sys0DelTime == '' "> ,f_sys0_del_time= sysdate() </if> 		,f_sys0_del_state= 1 		</trim>		WHERE 1=1  		AND f_sys0_del_state = 0 		AND f_id=#{item.id}    	</foreach>    </update>        <!-- 根据序列号删除(用户所持消费券表)信息。 -->    <sql id="delete_userCoupon">		DELETE FROM t_user_coupon WHERE f_id=#{_parameter}    </sql>    <delete id="delete_userCoupon" parameterType="java.lang.String">		<include refid="userCouponBase.delete_userCoupon"/>    </delete>        <!-- 根据序列号批量删除(用户所持消费券表)信息。 -->    <delete id="delete_userCoupon_Batch" parameterType="java.util.List">		DELETE FROM t_user_coupon WHERE 1=1 AND f_id IN 		<foreach item="item" collection="list" open="(" separator="," close=")">			#{item}		</foreach>    </delete>    </mapper>